tf3d/__init__.py
tf3d/chaining.py
tf3d/pinhole_projection.py
tf3d/rt_matrix.py
tf3d-1.2.dist-info/LICENSE
tf3d-1.2.dist-info/METADATA
tf3d-1.2.dist-info/WHEEL
tf3d-1.2.dist-info/top_level.txt
tf3d-1.2.dist-info/RECORD
