Metadata-Version: 2.1
Name: tf3d
Version: 1.2
Summary: UNKNOWN
Home-page: UNKNOWN
Author: Michael Fuerst
Author-email: mail@michaelfuerst.de
License: MIT
Platform: UNKNOWN
Requires-Dist: numpy (>=1.19.0)
Requires-Dist: pyquaternion (>=0.9.9)
Provides-Extra: dev
Requires-Dist: nose2 ; extra == 'dev'
Requires-Dist: packaging ; extra == 'dev'
